cohmetrix_br/BioBase_LIWC_CM.csv
cohmetrix_br/TecBase_LIWC.csv
cohmetrix_br/__init__.py
cohmetrix_br/essay_dataset.csv
cohmetrix_br/features_LIWC.py
cohmetrix_br/feedbackPortugueseDataset.csv
cohmetrix_br/liwc.py
cohmetrix_br/main.py
cohmetrix_br/redacao.txt
cohmetrix_br/run_cohmetrix_csv.py
cohmetrix_br-0.1.0.dist-info/WHEEL
cohmetrix_br-0.1.0.dist-info/METADATA
cohmetrix_br-0.1.0.dist-info/RECORD
