Metadata-Version: 2.1
Name: cohmetrix-br
Version: 0.1.0
Summary: A Brazilian-Portuguese version of cohmetrix
Author: Rafael Melo
Author-email: rafaelflmello@gmail.com
Requires-Python: >=3.9,<4.0
Classifier: Programming Language :: Python :: 3
Classifier: Programming Language :: Python :: 3.9
Requires-Dist: Pyphen (>=0.10.0,<0.11.0)
Requires-Dist: Unidecode (>=1.2.0,<2.0.0)
Requires-Dist: billiard (>=3.6.4,<4.0.0)
Requires-Dist: fastapi (>=0.65.2,<0.66.0)
Requires-Dist: gensim (>=4.0.1,<5.0.0)
Requires-Dist: lexical-diversity (>=0.1.1,<0.2.0)
Requires-Dist: nltk (>=3.6.2,<4.0.0)
Requires-Dist: numpy (>=1.20.3,<2.0.0)
Requires-Dist: orjson (>=3.5.3,<4.0.0)
Requires-Dist: pandas (>=1.2.4,<2.0.0)
Requires-Dist: scikit-learn (>=0.24.2,<0.25.0)
Requires-Dist: sklearn (>=0.0,<0.1)
Requires-Dist: spacy (>=3.0.6,<4.0.0)
Requires-Dist: textblob (>=0.15.3,<0.16.0)
Requires-Dist: uvicorn (>=0.14.0,<0.15.0)
